attnax/__init__.py
attnax/attention.py
attnax/blocks.py
attnax/config.py
attnax/embeddings.py
attnax/encoder.py
attnax/feedforward.py
attnax/masking.py
attnax-0.1.0.dist-info/licenses/LICENSE
attnax-0.1.0.dist-info/METADATA
attnax-0.1.0.dist-info/WHEEL
attnax-0.1.0.dist-info/top_level.txt
attnax-0.1.0.dist-info/RECORD
