Metadata-Version: 2.4
Name: attnax
Version: 0.1.0
Summary: Composable attention and transformer components for JAX.
Author-email: Glib Tkachenko <gtkachenko7@gmail.com>
License: Apache-2.0
Keywords: python,jax,machine learning,transformers,attention
Classifier: Development Status :: 3 - Alpha
Classifier: Environment :: Console
Classifier: Intended Audience :: Developers
Classifier: Intended Audience :: Science/Research
Classifier: Operating System :: OS Independent
Classifier: Programming Language :: Python
Classifier: Programming Language :: Python :: 3
Classifier: Programming Language :: Python :: 3.9
Classifier: Programming Language :: Python :: 3.10
Classifier: Programming Language :: Python :: 3.11
Classifier: Programming Language :: Python :: 3.12
Classifier: Topic :: Scientific/Engineering :: Artificial Intelligence
Classifier: Topic :: Software Development :: Libraries :: Python Modules
Requires-Python: >=3.9
License-File: LICENSE
Requires-Dist: jax>=0.4.0
Requires-Dist: flax>=0.8.0
Requires-Dist: optax>=0.1.0
Provides-Extra: test
Requires-Dist: pytest>=7.0; extra == "test"
Dynamic: license-file
